{
  "appPageId" : "d6c2b6a0-eb00-47fe-9721-432975119ae3",
  "componentName" : "siteforce:sldsOneColLayout",
  "id" : "1c23bcad-84ab-45ac-a9f8-e8331087bf33",
  "label" : "Record Detail",
  "regions" : [ {
    "id" : "5c6e3253-746b-43c4-a8ee-c725cefa12b2",
    "regionName" : "header",
    "type" : "region"
  }, {
    "components" : [ {
      "componentAttributes" : {
        "recordId" : "{!recordId}"
      },
      "componentName" : "forceCommunity:recordHeadline",
      "id" : "6b807288-1fbc-446c-ac4b-f8cd229e2c21",
      "renderPriority" : "NEUTRAL",
      "renditionMap" : { },
      "type" : "component"
    }, {
      "componentAttributes" : {
        "detailsTabLabel" : "Details",
        "discussionsTabLabel" : "Feed",
        "recordId" : "{!recordId}",
        "relatedTabLabel" : "Related",
        "tab1Type" : "details",
        "tab2Type" : "related",
        "tab3Type" : "chatter",
        "tab4Type" : "none",
        "timelineTabLabel" : "Activity"
      },
      "componentName" : "forceCommunity:recordHomeTabs",
      "id" : "2aa80905-4c17-4a4d-bb01-07513d599cd8",
      "renderPriority" : "NEUTRAL",
      "renditionMap" : { },
      "type" : "component"
    } ],
    "id" : "309c7b26-a6a7-424c-bd80-2bf7b71c02e0",
    "regionName" : "content",
    "type" : "region"
  }, {
    "id" : "0de2a778-602d-45a8-b4fc-dcaf1d3a2108",
    "regionName" : "footer",
    "type" : "region"
  }, {
    "components" : [ {
      "componentAttributes" : {
        "description" : "",
        "metaTags" : "",
        "title" : "{!Record._Object}: {!Record._Title}"
      },
      "componentName" : "forceCommunity:seoAssistant",
      "id" : "cfd91d73-5c9c-49e4-a140-2ce923b09153",
      "renderPriority" : "NEUTRAL",
      "renditionMap" : { },
      "type" : "component"
    } ],
    "id" : "ae039d7d-8bcb-4783-8abd-7d89064aad56",
    "regionName" : "sfdcHiddenRegion",
    "type" : "region"
  } ],
  "themeLayoutType" : "Inner",
  "type" : "view",
  "viewType" : "detail"
}